selahx/__init__.py
selahx/assets/ec2_ssh_host.png
selahx/assets/slx_client_help.png
selahx/assets/slx_save.png
selahx/assets/slx_terminal.png
selahx/cli.py
selahx/client.py
selahx/ec2/setup.sh
selahx/save_files.py
selahx_client-0.1.0.dist-info/METADATA
selahx_client-0.1.0.dist-info/WHEEL
selahx_client-0.1.0.dist-info/entry_points.txt
selahx_client-0.1.0.dist-info/licenses/LICENSE
selahx_client-0.1.0.dist-info/RECORD
