Metadata-Version: 2.4
Name: selahx_client
Version: 0.1.0
Summary: Remote Access Tool — Fast and lightweight CLI experience.
License: MIT
License-File: LICENSE
Author: Abiy
Author-email: abiy.dema@gmail.com
Requires-Python: >=3.11,<4.0
Classifier: License :: OSI Approved :: MIT License
Classifier: Programming Language :: Python :: 3
Classifier: Programming Language :: Python :: 3.11
Classifier: Programming Language :: Python :: 3.12
Classifier: Programming Language :: Python :: 3.13
Classifier: Programming Language :: Python :: 3.14
Requires-Dist: argparse (>=1.4.0,<2.0.0)
Requires-Dist: readchar (>=4.2.1,<5.0.0)
Requires-Dist: tabulate (>=0.9.0,<0.10.0)
Requires-Dist: typer (>=0.20.0,<0.21.0)
Project-URL: Documentation, https://github.com/Haabiy/selahx_client#readme
Project-URL: Repository, https://github.com/Haabiy/selahx_client
